a2c_ppo_acktr/__init__.py
a2c_ppo_acktr/arguments.py
a2c_ppo_acktr/distributions.py
a2c_ppo_acktr/envs.py
a2c_ppo_acktr/model.py
a2c_ppo_acktr/storage.py
a2c_ppo_acktr/utils.py
a2c_ppo_acktr/wrap_env.py
a2c_ppo_acktr/algo/__init__.py
a2c_ppo_acktr/algo/a2c_acktr.py
a2c_ppo_acktr/algo/gail.py
a2c_ppo_acktr/algo/kfac.py
a2c_ppo_acktr/algo/ppo.py
gail_experts/__init__.py
gail_experts/convert_to_pytorch.py
submql-0.0.1.dist-info/LICENSE
submql-0.0.1.dist-info/METADATA
submql-0.0.1.dist-info/WHEEL
submql-0.0.1.dist-info/top_level.txt
submql-0.0.1.dist-info/RECORD
